QUANTAXIS_RandomPrice/__init__.py
quantaxis_randomprice-1.1.dist-info/METADATA
quantaxis_randomprice-1.1.dist-info/WHEEL
quantaxis_randomprice-1.1.dist-info/entry_points.txt
quantaxis_randomprice-1.1.dist-info/top_level.txt
quantaxis_randomprice-1.1.dist-info/zip-safe
quantaxis_randomprice-1.1.dist-info/RECORD
